{
  "generatedAt": "2026-02-24T08:37:00Z",
  "generatedBy": "nba-agent",
  "feedType": "nba",
  "title": "NBA Daily Fast Break",
  "subtitle": "Your essential guide to all the action from February 23-24, 2026",
  "badge": "Updated Today",
  "sections": [
    {
      "id": "breaking-news",
      "title": "Breaking News",
      "cardType": "breaking",
      "layout": "featured",
      "items": [
        {
          "id": "giannis-trade-rumors-022426",
          "headline": "Giannis Antetokounmpo Trade Speculation Heats Up for Offseason",
          "summary": "Despite publicly declaring loyalty to the Bucks, NBA insiders are forecasting Giannis Antetokounmpo's potential departure after this season, with the Miami Heat and Los Angeles Lakers identified as primary suitors.",
          "tags": [
            "Trade Rumors",
            "Bucks",
            "Heat",
            "Lakers"
          ]
        },
        {
          "id": "lebron-cavs-rumors-022426",
          "headline": "LeBron James Eyeing Cavaliers Return on Historic Pay Cut?",
          "summary": "Speculation suggests LeBron James could rejoin the Cleveland Cavaliers in his final career stages, potentially taking a veteran minimum salary. This move would mark the largest pay cut in NBA history.",
          "tags": [
            "Trade Rumors",
            "Lakers",
            "Cavaliers",
            "LeBron James"
          ]
        },
        {
          "id": "avdija-injury-022426",
          "headline": "Deni Avdija Sidelined with Back Injury",
          "summary": "Portland Trail Blazers' Israeli guard Deni Avdija will miss Tuesday's game against Minnesota due to an aggravated lower back injury. Avdija re-injured his back on Sunday against the Suns, playing less than a minute after weeks of battling the issue.",
          "tags": [
            "Injury Report",
            "Trail Blazers",
            "Deni Avdija",
            "Israeli Player"
          ]
        },
        {
          "id": "brooks-fractured-hand-022426",
          "headline": "Dillon Brooks Out with Fractured Left Hand",
          "summary": "Phoenix Suns forward Dillon Brooks sustained a fractured left hand during Saturday's double-overtime win against the Orlando Magic. Brooks, who has been having a career-best season averaging 20.9 points per game, is out indefinitely.",
          "tags": [
            "Injury Report",
            "Suns",
            "Dillon Brooks"
          ]
        },
        {
          "id": "murray-return-022426",
          "headline": "Dejounte Murray Set for Pelicans Debut After Achilles Injury",
          "summary": "New Orleans Pelicans guard Dejounte Murray is expected to make his season debut Tuesday against the Golden State Warriors, returning from an Achilles injury sustained in January 2025.",
          "tags": [
            "Injury Update",
            "Pelicans",
            "Dejounte Murray",
            "Return"
          ]
        }
      ]
    },
    {
      "id": "last-nights-games",
      "title": "Last Night's Games (Feb 23, 2026)",
      "cardType": "game",
      "layout": "grid",
      "items": [
        {
          "id": "sas-det-022326",
          "headline": "Spurs Extend Win Streak to Nine, Humble Pistons",
          "summary": "The San Antonio Spurs continued their dominant run, beating the Detroit Pistons on the road.",
          "tags": [
            "Spurs",
            "Pistons",
            "Final"
          ],
          "homeTeam": "DET",
          "awayTeam": "SAS",
          "homeScore": 103,
          "awayScore": 114,
          "gameStatus": "final"
        },
        {
          "id": "hou-uta-022326",
          "headline": "Rockets Soar Past Jazz at Home",
          "summary": "The Houston Rockets secured a comfortable victory against the Utah Jazz.",
          "tags": [
            "Rockets",
            "Jazz",
            "Final"
          ],
          "homeTeam": "HOU",
          "awayTeam": "UTA",
          "homeScore": 125,
          "awayScore": 105,
          "gameStatus": "final"
        },
        {
          "id": "bos-lal-022326",
          "headline": "Celtics Dominate Lakers",
          "summary": "The Boston Celtics decisively defeated the Los Angeles Lakers.",
          "tags": [
            "Celtics",
            "Lakers",
            "Final"
          ],
          "homeTeam": "BOS",
          "awayTeam": "LAL",
          "homeScore": 111,
          "awayScore": 89,
          "gameStatus": "final"
        },
        {
          "id": "tor-mil-022326",
          "headline": "Raptors Overpower Bucks",
          "summary": "The Toronto Raptors clinched a strong win against the Milwaukee Bucks.",
          "tags": [
            "Raptors",
            "Bucks",
            "Final"
          ],
          "homeTeam": "TOR",
          "awayTeam": "MIL",
          "homeScore": 122,
          "awayScore": 94,
          "gameStatus": "final"
        },
        {
          "id": "atl-brk-022326",
          "headline": "Hawks Defeat Nets",
          "summary": "The Atlanta Hawks emerged victorious over the Brooklyn Nets.",
          "tags": [
            "Hawks",
            "Nets",
            "Final"
          ],
          "homeTeam": "ATL",
          "awayTeam": "BRK",
          "homeScore": 115,
          "awayScore": 104,
          "gameStatus": "final"
        },
        {
          "id": "dal-ind-022326",
          "headline": "Mavericks Snap Skid Against Pacers",
          "summary": "The Dallas Mavericks ended their 10-game losing streak with a win over the Indiana Pacers.",
          "tags": [
            "Mavericks",
            "Pacers",
            "Final"
          ],
          "homeTeam": "DAL",
          "awayTeam": "IND",
          "homeScore": 134,
          "awayScore": 130,
          "gameStatus": "final"
        },
        {
          "id": "sac-mem-022326",
          "headline": "Kings End 16-Game Skid with Win Over Grizzlies",
          "summary": "The Sacramento Kings broke their long losing streak by defeating the Memphis Grizzlies.",
          "tags": [
            "Kings",
            "Grizzlies",
            "Final"
          ],
          "homeTeam": "MEM",
          "awayTeam": "SAC",
          "homeScore": 0,
          "awayScore": 0,
          "gameStatus": "final"
        }
      ]
    },
    {
      "id": "upcoming-games",
      "title": "Games Today/Tonight (Feb 24, 2026)",
      "cardType": "game",
      "layout": "list",
      "items": [
        {
          "id": "phi-ind-022426",
          "headline": "76ers vs. Pacers",
          "summary": "Eastern Conference matchup in Indianapolis.",
          "tags": [
            "76ers",
            "Pacers",
            "Scheduled"
          ],
          "homeTeam": "IND",
          "awayTeam": "PHI",
          "gameStatus": "scheduled",
          "gameTime": "7:00 PM ET"
        },
        {
          "id": "chi-cha-022426",
          "headline": "Bulls vs. Hornets",
          "summary": "Chicago hosts Charlotte in this regular season clash.",
          "tags": [
            "Bulls",
            "Hornets",
            "Scheduled"
          ],
          "homeTeam": "CHI",
          "awayTeam": "CHA",
          "gameStatus": "scheduled",
          "gameTime": "7:00 PM ET"
        },
        {
          "id": "phx-bos-022426",
          "headline": "Suns vs. Celtics",
          "summary": "Phoenix takes on Boston in a cross-conference battle.",
          "tags": [
            "Suns",
            "Celtics",
            "Scheduled"
          ],
          "homeTeam": "PHX",
          "awayTeam": "BOS",
          "gameStatus": "scheduled",
          "gameTime": "7:00 PM ET"
        },
        {
          "id": "nop-gsw-022426",
          "headline": "Pelicans vs. Warriors",
          "summary": "Dejounte Murray returns for the Pelicans against the Warriors.",
          "tags": [
            "Pelicans",
            "Warriors",
            "Scheduled"
          ],
          "homeTeam": "NOP",
          "awayTeam": "GSW",
          "gameStatus": "scheduled",
          "gameTime": "8:00 PM ET"
        },
        {
          "id": "lal-orl-022426",
          "headline": "Lakers vs. Magic",
          "summary": "Luka Doncic and the Lakers host the Orlando Magic.",
          "tags": [
            "Lakers",
            "Magic",
            "Scheduled"
          ],
          "homeTeam": "LAL",
          "awayTeam": "ORL",
          "gameStatus": "scheduled",
          "gameTime": "10:30 PM ET"
        },
        {
          "id": "min-nyk-022426",
          "headline": "Timberwolves vs. Knicks",
          "summary": "Action from Madison Square Garden.",
          "tags": [
            "Timberwolves",
            "Knicks",
            "Scheduled"
          ],
          "homeTeam": "NYK",
          "awayTeam": "MIN",
          "gameStatus": "scheduled",
          "gameTime": "7:00 PM ET"
        }
      ]
    },
    {
      "id": "player-highlights",
      "title": "Player Highlights",
      "cardType": "stat",
      "layout": "grid",
      "items": [
        {
          "id": "vassell-022326",
          "headline": "Devin Vassell's Sharpshooting Leads Spurs",
          "statLabel": "28 PTS",
          "statValue": "7 3PM",
          "statContext": "vs. DET, Feb 23",
          "tags": [
            "Spurs",
            "Scoring",
            "Three-Pointers"
          ]
        },
        {
          "id": "wembanyama-022326",
          "headline": "Wemby's Monster Performance",
          "statLabel": "21 PTS, 17 REB, 6 BLK, 4 AST",
          "statValue": "All-Around Dominance",
          "statContext": "vs. DET, Feb 23",
          "tags": [
            "Spurs",
            "Rookie",
            "Double-Double",
            "Blocks"
          ]
        },
        {
          "id": "smithjr-022326",
          "headline": "Jabari Smith Jr. Ignites Rockets",
          "statLabel": "31 PTS, 9 REB",
          "statValue": "Career-High First Quarter",
          "statContext": "vs. UTA, Feb 23",
          "tags": [
            "Rockets",
            "Scoring",
            "Rebounding"
          ]
        },
        {
          "id": "thompson-022326",
          "headline": "Amen Thompson Efficient for Houston",
          "statLabel": "20 PTS, 7 REB, 3 AST, 2 STL",
          "statValue": "8-9 FG Shooting",
          "statContext": "vs. UTA, Feb 23",
          "tags": [
            "Rockets",
            "Efficiency",
            "Rookie"
          ]
        },
        {
          "id": "duren-022326",
          "headline": "Jalen Duren's Double-Double Effort",
          "statLabel": "25 PTS, 14 REB",
          "statValue": "Pistons Big Man Shines",
          "statContext": "vs. SAS, Feb 23",
          "tags": [
            "Pistons",
            "Double-Double",
            "Rebounding"
          ]
        },
        {
          "id": "brown-pritchard-022326",
          "headline": "Celtics Duo Leads to Victory",
          "statLabel": "Jaylen Brown 32 PTS, Peyton Pritchard 30 PTS",
          "statValue": "High Scoring Performances",
          "statContext": "vs. LAL, Feb 23",
          "tags": [
            "Celtics",
            "Scoring"
          ]
        },
        {
          "id": "quickley-022326",
          "headline": "Quickley Powers Raptors Offense",
          "statLabel": "32 PTS",
          "statValue": "Top Scorer for Toronto",
          "statContext": "vs. MIL, Feb 23",
          "tags": [
            "Raptors",
            "Scoring"
          ]
        },
        {
          "id": "johnson-022326",
          "headline": "Jaylen Johnson's Double-Double",
          "statLabel": "26 PTS, 12 REB",
          "statValue": "Big Night for Hawks Forward",
          "statContext": "vs. BRK, Feb 23",
          "tags": [
            "Hawks",
            "Double-Double"
          ]
        },
        {
          "id": "siakam-022326",
          "headline": "Pascal Siakam's Strong Scoring",
          "statLabel": "30 PTS",
          "statValue": "Paces Pacers Offense",
          "statContext": "vs. DAL, Feb 23",
          "tags": [
            "Pacers",
            "Scoring"
          ]
        }
      ]
    },
    {
      "id": "around-the-league",
      "title": "Around the League",
      "cardType": "article",
      "layout": "list",
      "items": [
        {
          "id": "western-standings-022426",
          "headline": "Western Conference Standings Update",
          "summary": "The Oklahoma City Thunder (44-14) lead the Western Conference, followed by the San Antonio Spurs (40-16). The Houston Rockets improved to 35-21, moving into third place.",
          "tags": [
            "Standings",
            "Western Conference"
          ]
        },
        {
          "id": "eastern-standings-022426",
          "headline": "Eastern Conference Standings Update",
          "summary": "The Detroit Pistons (42-13) maintain their lead in the Eastern Conference.",
          "tags": [
            "Standings",
            "Eastern Conference"
          ]
        },
        {
          "id": "lakers-allen-rumors-022426",
          "headline": "Lakers Reportedly Eyeing Jarrett Allen Trade",
          "summary": "The Los Angeles Lakers are reportedly exploring a trade for Cleveland Cavaliers center Jarrett Allen to enhance their roster around Luka Doncic and LeBron James. Austin Reaves and future draft picks are rumored assets.",
          "tags": [
            "Trade Rumors",
            "Lakers",
            "Cavaliers"
          ]
        },
        {
          "id": "kd-2028-olympics-022426",
          "headline": "Kevin Durant Expresses Interest in 2028 Olympics",
          "summary": "Houston Rockets forward Kevin Durant has informed USA Basketball that he would like to be considered for the U.S. men's team for the 2028 Los Angeles Olympics, despite being nearly 40 years old by then.",
          "tags": [
            "Team USA",
            "Kevin Durant",
            "Olympics"
          ]
        },
        {
          "id": "player-stat-leaders-022426",
          "headline": "League Leaders in Key Statistical Categories",
          "summary": "Luka Doncic leads the league in scoring (32.8 PPG), while Nikola Jokic tops both rebounds (12.5 RPG) and assists (10.5 APG). Shai Gilgeous-Alexander holds the lead in Win Shares (11.4).",
          "tags": [
            "Stats",
            "League Leaders"
          ]
        }
      ]
    }
  ]
}