{
  "generatedAt": "2026-06-08T12:22:00Z",
  "generatedBy": "nba-agent",
  "feedType": "nba",
  "title": "NBA Daily Digest",
  "subtitle": "June 8, 2026 - NBA Finals heating up!",
  "badge": "LIVE",
  "sections": [
    {
      "id": "breaking-news",
      "title": "Breaking News",
      "cardType": "breaking",
      "layout": "featured",
      "items": [
        {
          "id": "finals-game3-preview",
          "headline": "Knicks Eye Commanding 3-0 Lead in NBA Finals Game 3 Tonight!",
          "summary": "The New York Knicks are set to host the San Antonio Spurs in Game 3 of the NBA Finals tonight at Madison Square Garden, holding a dominant 2-0 series advantage. New York is just two wins away from their first championship since 1973, with tickets reportedly soaring to unprecedented prices as 'Knicks fever' grips the city.",
          "tags": [
            "NBA Finals",
            "NYK",
            "SAS",
            "Game 3",
            "Knicks Fever"
          ]
        },
        {
          "id": "trade-rumors-brown-giannis",
          "headline": "Blockbuster Trade Rumors Swirl: Jaylen Brown to Hawks, Giannis Future Uncertain",
          "summary": "Speculation is mounting around potential seismic shifts across the league. A proposed three-team trade could send Celtics star Jaylen Brown to the Atlanta Hawks, while the future of two-time MVP Giannis Antetokounmpo with the Milwaukee Bucks remains a hot topic, with the Miami Heat reportedly emerging as frontrunners amidst doubts about a move to Boston.",
          "tags": [
            "Trade Rumors",
            "Celtics",
            "Hawks",
            "Bucks",
            "Heat"
          ]
        }
      ]
    },
    {
      "id": "last-nights-games",
      "title": "Last Night's Games",
      "cardType": "game",
      "layout": "grid",
      "items": [
        {
          "id": "june7-no-games",
          "headline": "No NBA Games Scheduled",
          "summary": "There were no NBA games played on Sunday, June 7, 2026. The league is preparing for Game 3 of the NBA Finals tonight.",
          "tags": [
            "No Games"
          ]
        },
        {
          "id": "finals-game2-recap",
          "headline": "Flashback: Knicks Edge Spurs in Thrilling Game 2 on Friday!",
          "summary": "In the last game played, on Friday, June 5, the New York Knicks secured a nail-biting 105-104 victory over the San Antonio Spurs in Game 2 of the NBA Finals. Jalen Brunson hit the decisive free throw, while Karl-Anthony Towns dominated the boards.",
          "homeTeam": "NYK",
          "awayTeam": "SAS",
          "homeScore": 105,
          "awayScore": 104,
          "gameStatus": "final",
          "gameTime": "June 5, 2026",
          "tags": [
            "NBA Finals",
            "NYK Win"
          ]
        }
      ]
    },
    {
      "id": "upcoming-games",
      "title": "Tonight's Games",
      "cardType": "game",
      "layout": "list",
      "items": [
        {
          "id": "finals-game3",
          "headline": "NBA Finals Game 3: Spurs at Knicks",
          "summary": "The San Antonio Spurs travel to Madison Square Garden to face the New York Knicks in a pivotal Game 3 of the NBA Finals. The Knicks lead the series 2-0. Tip-off is scheduled for 8:30 PM ET.",
          "homeTeam": "New York Knicks",
          "awayTeam": "San Antonio Spurs",
          "homeScore": null,
          "awayScore": null,
          "gameStatus": "scheduled",
          "gameTime": "8:30 PM ET",
          "tags": [
            "NBA Finals",
            "Live",
            "ESPN",
            "ABC"
          ]
        }
      ]
    },
    {
      "id": "player-highlights",
      "title": "Player Highlights",
      "cardType": "stat",
      "layout": "grid",
      "items": [
        {
          "id": "brunson-clutch-game2",
          "headline": "Brunson Delivers Clutch in Game 2",
          "summary": "Jalen Brunson spearheaded the Knicks' Game 2 victory with 20 points, including the go-ahead free throw in the final seconds. He also dropped 30 points in Game 1, with 13 coming in the fourth quarter.",
          "statLabel": "20 PTS, GW FT (Game 2)",
          "statValue": "Jalen Brunson (NYK)",
          "statContext": "NBA Finals Game 2"
        },
        {
          "id": "towns-boards-game2",
          "headline": "KAT Dominates Glass in Game 2",
          "summary": "Karl-Anthony Towns was a force for the Knicks in Game 2, contributing 21 points, a massive 13 rebounds, and 4 assists.",
          "statLabel": "21 PTS, 13 REB, 4 AST",
          "statValue": "Karl-Anthony Towns (NYK)",
          "statContext": "NBA Finals Game 2"
        },
        {
          "id": "wembanyama-playoff-force",
          "headline": "Wemby's Playoff Dominance",
          "summary": "Despite the Spurs' 0-2 deficit, Victor Wembanyama has been a statistical marvel in the playoffs, averaging 23.6 points, 10.7 rebounds, and an astounding 3.53 blocks per game.",
          "statLabel": "23.6 PPG, 10.7 RPG, 3.53 BPG",
          "statValue": "Victor Wembanyama (SAS)",
          "statContext": "2026 NBA Playoffs"
        },
        {
          "id": "avdija-playin-heroics",
          "headline": "Deni Avdija's Play-In Masterclass",
          "summary": "Israeli standout Deni Avdija had a career-defining performance in the Play-In Tournament, erupting for 41 points, 12 assists, 7 rebounds, and 2 blocks to lead the Blazers to the playoffs. He also averaged over 25 points per game during the regular season.",
          "statLabel": "41 PTS, 12 AST, 7 REB, 2 BLK",
          "statValue": "Deni Avdija (POR)",
          "statContext": "Play-In Tournament Game"
        }
      ]
    },
    {
      "id": "around-the-league",
      "title": "Around the League",
      "cardType": "article",
      "layout": "list",
      "items": [
        {
          "id": "injury-mitchell-robinson",
          "headline": "Mitchell Robinson Cleared for Game 3 Despite Hand Fracture",
          "summary": "Knicks center Mitchell Robinson has been cleared to play in Game 3 of the NBA Finals against the Spurs, despite suffering a fractured right 5th metacarpal.",
          "tags": [
            "Injury Update",
            "NYK"
          ]
        },
        {
          "id": "divincenzo-out",
          "headline": "Donte DiVincenzo Out for Postseason with Torn Achilles",
          "summary": "In unfortunate news, Donte DiVincenzo has been diagnosed with a torn right Achilles tendon and will miss the remainder of the postseason.",
          "tags": [
            "Injury Update",
            "Season-Ending"
          ]
        },
        {
          "id": "mobley-giannis-trade",
          "headline": "Cavs Held Firm on Mobley, Refused Giannis Trade",
          "summary": "The Cleveland Cavaliers reportedly made the strategic decision to refuse to trade Evan Mobley for Giannis Antetokounmpo, signaling their long-term commitment to Mobley.",
          "tags": [
            "Trade News",
            "Cavs",
            "Bucks"
          ]
        },
        {
          "id": "hachimura-trade-rumor",
          "headline": "Rui Hachimura to Clippers in Proposed Three-Team Trade",
          "summary": "A new trade idea suggests Rui Hachimura could be on the move, swapping the Lakers for the Clippers in a three-team deal.",
          "tags": [
            "Trade Rumors",
            "Lakers",
            "Clippers"
          ]
        }
      ]
    }
  ]
}