{
  "generatedAt": "2026-04-01T08:14:00Z",
  "generatedBy": "stocks-agent",
  "feedType": "stocks",
  "title": "Daily Market Digest: April 1, 2026",
  "subtitle": "Pre-market buoyancy as geopolitical tensions ease",
  "badge": "LIVE",
  "sections": [
    {
      "id": "market-pulse",
      "title": "Market Pulse",
      "cardType": "breaking",
      "layout": "featured",
      "items": [
        {
          "id": "market-summary-april-1",
          "headline": "U.S. Futures Point Higher on Geopolitical Optimism and Easing Oil Prices",
          "summary": "U.S. stock futures are showing upward momentum in pre-market trading on Wednesday, April 1, 2026. The positive sentiment is largely driven by growing hopes that the conflict in Iran may be nearing an end following recent comments from President Donald Trump, signaling a potential U.S. exit. This de-escalation, coupled with easing oil prices, is providing a boost to market sentiment after a period of volatility. Major indices saw significant gains in the previous cash session (Tuesday, March 31, 2026). However, some analysts caution that elevated oil prices, despite recent drops, could still signal lingering risks.",
          "tags": [
            "Pre-Market",
            "Market Sentiment",
            "Geopolitics",
            "Oil Prices"
          ],
          "timestamp": "2026-04-01T08:14:00Z"
        }
      ]
    },
    {
      "id": "major-indices",
      "title": "Major Indices",
      "cardType": "stat",
      "layout": "grid",
      "items": [
        {
          "id": "sp500-futures",
          "statLabel": "S&P 500 Futures",
          "statValue": "Up 0.70%",
          "statContext": "Pre-market trading, 3:21 a.m. EDT.",
          "direction": "up"
        },
        {
          "id": "nasdaq-futures",
          "statLabel": "NASDAQ 100 Futures",
          "statValue": "Up 0.99%",
          "statContext": "Pre-market trading, 3:21 a.m. EDT.",
          "direction": "up"
        },
        {
          "id": "dow-futures",
          "statLabel": "Dow Jones Futures",
          "statValue": "Up 0.64%",
          "statContext": "Pre-market trading, 3:21 a.m. EDT.",
          "direction": "up"
        },
        {
          "id": "us500-index",
          "statLabel": "US500 Index",
          "statValue": "6581 points",
          "statContext": "Rose 0.81% on April 1, 2026.",
          "direction": "up"
        }
      ]
    },
    {
      "id": "top-movers",
      "title": "Top Movers (Pre-Market Indications)",
      "cardType": "stock",
      "layout": "grid",
      "items": [
        {
          "id": "meta-gain",
          "headline": "Meta Platforms shows strong momentum",
          "ticker": "$META",
          "price": "N/A",
          "change": "N/A",
          "changePercent": "+6.7%",
          "direction": "up",
          "summary": "Meta surged in recent trading, contributing to optimism in the tech sector."
        },
        {
          "id": "marvell-gain",
          "headline": "Marvell Technology soars on strategic partnership",
          "ticker": "$MRVL",
          "price": "N/A",
          "change": "N/A",
          "changePercent": "+13.0%",
          "direction": "up",
          "summary": "Marvell Technology is pacing the Nasdaq after unveiling a strategic partnership and a $2 billion investment from Nvidia."
        },
        {
          "id": "nvidia-gain",
          "headline": "Nvidia extends gains, reinforcing tech optimism",
          "ticker": "$NVDA",
          "price": "N/A",
          "change": "N/A",
          "changePercent": "+5.6%",
          "direction": "up",
          "summary": "Shares of Nvidia advanced, reinforcing optimism across the technology sector."
        },
        {
          "id": "nike-decline",
          "headline": "Nike extends declines on revenue projection",
          "ticker": "$NKE",
          "price": "N/A",
          "change": "N/A",
          "changePercent": "N/A",
          "direction": "down",
          "summary": "Nike Inc.'s shares extended declines after the company projected a drop in revenue for the current quarter, exacerbating investor concerns related to ongoing geopolitical events."
        }
      ]
    },
    {
      "id": "market-news",
      "title": "Market News",
      "cardType": "article",
      "layout": "list",
      "items": [
        {
          "id": "iran-conflict-hopes",
          "headline": "Hopes for Iran Conflict De-escalation Boost Market Sentiment",
          "summary": "Optimism over a potential end to the conflict in Iran is a significant driver of today's market buoyancy. President Donald Trump indicated a potential U.S. exit from Iran, contributing to a risk-on environment. This news is helping to offset some of the geopolitical concerns that have recently weighed on markets.",
          "tags": [
            "Geopolitics",
            "Market Sentiment",
            "Oil Prices"
          ],
          "timestamp": "2026-04-01T08:14:00Z"
        },
        {
          "id": "economic-data-april-1",
          "headline": "Key Economic Data Releases Scheduled for April 1, 2026",
          "summary": "Investors will be closely watching several key economic data releases throughout the day. These include the U.S. ADP Employment Report for March, U.S. Retail Sales for February (a delayed report), and the ISM Manufacturing Index for March. Additionally, Business Inventories for January are expected. These reports will provide further insights into the health and direction of the U.S. economy.",
          "tags": [
            "Economic Data",
            "ADP",
            "Retail Sales",
            "ISM Manufacturing"
          ],
          "timestamp": "2026-04-01T08:14:00Z"
        },
        {
          "id": "fed-speakers",
          "headline": "Federal Reserve Officials Set to Speak Today",
          "summary": "St. Louis Fed President Alberto Musalem and Fed Governor Michael Barr are scheduled to deliver remarks today. Market participants will be keen to hear their perspectives on the current economic outlook, inflation, and monetary policy, especially in light of recent geopolitical developments.",
          "tags": [
            "Federal Reserve",
            "Monetary Policy",
            "Economic Outlook"
          ],
          "timestamp": "2026-04-01T08:14:00Z"
        },
        {
          "id": "earnings-reports-april-1",
          "headline": "Several Companies Report Earnings Today",
          "summary": "A number of companies are scheduled to release their quarterly earnings reports today. Confirmed reports include MSC Industrial Direct Co ($MSM) before market open (Q2 2026), Penguin Solutions Inc. ($PENG) after market close (Q2 2026), and Synergy CHC Corp ($SNYR) before market open (Q4 2025). Conagra Brands ($CAG) is also slated to release its fiscal 2026 third-quarter earnings. NXT Energy Solutions Inc. ($NSFDF) has already reported a Q4 loss.",
          "tags": [
            "Earnings",
            "Corporate News"
          ],
          "timestamp": "2026-04-01T08:14:00Z"
        }
      ]
    }
  ]
}