{
  "generatedAt": "2026-05-05T13:11:00Z",
  "generatedBy": "stocks-agent",
  "feedType": "stocks",
  "title": "Daily Market Digest: May 5, 2026",
  "subtitle": "Market navigating geopolitical tensions and strong Q1 earnings",
  "badge": "LIVE",
  "sections": [
    {
      "id": "market-pulse",
      "title": "Market Pulse",
      "cardType": "breaking",
      "layout": "featured",
      "items": [
        {
          "id": "market-summary-may5",
          "headline": "U.S. Futures Edge Higher as Markets Weigh Geopolitical Risks Against Robust Earnings",
          "summary": "U.S. stock futures showed modest gains this morning, with the S&P 500, Nasdaq, and Dow futures all pointing upward, despite a flare-up in tensions between the U.S. and Iran near the Strait of Hormuz. This follows a mixed close on Monday, where major indices declined amid geopolitical fears. The market is currently balancing renewed concerns over Middle East stability and elevated oil prices with a stronger-than-expected Q1 2026 earnings season. Strong corporate profitability, particularly in technology and consumer discretionary, continues to provide underlying support, with blended earnings growth for the S&P 500 estimated around 27% year-over-year. However, some analysts note a lack of broad market participation in recent rallies, signaling caution. Not financial advice.",
          "tags": [
            "Market Overview",
            "Geopolitics",
            "Earnings",
            "Oil Prices"
          ],
          "timestamp": "2026-05-05T13:11:00Z"
        }
      ]
    },
    {
      "id": "major-indices",
      "title": "Major Indices Performance",
      "cardType": "stat",
      "layout": "grid",
      "items": [
        {
          "id": "sp500-performance",
          "statLabel": "S&P 500",
          "statValue": "7,200.75",
          "statContext": "Closed -0.4% Monday. Futures +0.3% pre-market."
        },
        {
          "id": "nasdaq-performance",
          "statLabel": "NASDAQ Composite",
          "statValue": "25,067.8",
          "statContext": "Closed -0.19% Monday. Futures +0.5% pre-market."
        },
        {
          "id": "dow-performance",
          "statLabel": "Dow Jones Ind. Avg.",
          "statValue": "48,941.90",
          "statContext": "Closed -1.1% Monday. Futures +0.1% pre-market."
        }
      ]
    },
    {
      "id": "top-movers",
      "title": "Top Movers Today",
      "cardType": "stock",
      "layout": "grid",
      "items": [
        {
          "id": "pins-gainer",
          "headline": "Pinterest Soars on Strong Earnings",
          "summary": "Pinterest ($PINS) surged 17.5% in premarket trading after reporting first-quarter sales and profit that topped Wall Street estimates, driven by strong monthly active user growth.",
          "ticker": "$PINS",
          "price": "$24.53 (pre-market)",
          "change": "+$3.67",
          "changePercent": "+17.62%",
          "direction": "up"
        },
        {
          "id": "abibev-gainer",
          "headline": "Anheuser-Busch Inbev Jumps on Forecast Beat",
          "summary": "Anheuser-Busch Inbev ($ABIBEV) shares climbed over 6% in premarket trading after the Budweiser maker exceeded analyst sales and profit forecasts due to strong beer sales.",
          "ticker": "$ABIBEV",
          "price": "N/A",
          "change": "N/A",
          "changePercent": "+6%+",
          "direction": "up"
        },
        {
          "id": "gme-loser",
          "headline": "GameStop Slips After eBay Bid",
          "summary": "GameStop ($GME) was down slightly in premarket, continuing its slide from Monday's 10% drop, following its proposal to acquire online marketplace eBay for approximately $56 billion in cash and stock.",
          "ticker": "$GME",
          "price": "$23.78 (pre-market)",
          "change": "N/A",
          "changePercent": "Down slightly (pre-market)",
          "direction": "down"
        },
        {
          "id": "shph-loser",
          "headline": "Shuttle Pharmaceuticals Holdings Declines",
          "summary": "Shuttle Pharmaceuticals Holdings, Inc. ($SHPH) experienced a significant decline of 32.84%, making it one of the biggest losers in early May 2026.",
          "ticker": "$SHPH",
          "price": "$0.83",
          "change": "N/A",
          "changePercent": "-32.84%",
          "direction": "down"
        }
      ]
    },
    {
      "id": "market-news",
      "title": "Market News and Analysis",
      "cardType": "article",
      "layout": "list",
      "items": [
        {
          "id": "economic-data-trade",
          "headline": "U.S. Trade Deficit Widens in March 2026",
          "summary": "The U.S. goods and services deficit increased to $60.3 billion in March, marking a $2.5 billion rise from February's revised figure. March exports were $320.9 billion, and imports were $381.2 billion.",
          "tags": [
            "Economic Data",
            "Trade Deficit"
          ]
        },
        {
          "id": "fed-commentary",
          "headline": "New York Fed President Sees No Immediate Need for Rate Hikes",
          "summary": "The New York Federal Reserve President indicated today that there is currently no need to consider raising interest rates, though the future direction of rates remains uncertain.",
          "tags": [
            "Federal Reserve",
            "Interest Rates"
          ]
        },
        {
          "id": "geopolitical-oil",
          "headline": "Middle East Tensions Continue to Affect Oil Markets",
          "summary": "Geopolitical tensions in the Middle East escalated with reports of an exchange of fire between the U.S. and Iran near the Strait of Hormuz. While oil prices are easing slightly today, they remain elevated, with Brent crude at $113.30 per barrel and U.S. crude at $104.58 per barrel.",
          "tags": [
            "Geopolitics",
            "Oil Prices",
            "Middle East"
          ]
        },
        {
          "id": "earnings-q1-2026",
          "headline": "Q1 2026 Earnings Season Exceeding Expectations",
          "summary": "The Q1 2026 earnings season is proving largely positive, with over 60% of S&P 500 companies reporting results better than anticipated. Blended earnings growth for the S&P 500 is estimated at approximately 27% year-over-year. Notably, American Electric Power ($AEP), PayPal Holdings ($PYPL), and Ball Corporation ($BALL) all reported strong Q1 results today, reaffirming positive outlooks and guidance.",
          "tags": [
            "Earnings Reports",
            "Corporate Performance"
          ]
        },
        {
          "id": "sector-ai-demand",
          "headline": "AI Demand Fuels Growth in Technology and Durable Goods",
          "summary": "Demand for AI infrastructure continues to surge, with cloud compute platforms experiencing rising utilization. This trend is reflected in economic data, with durable orders up 0.8% in March, primarily driven by a 3.6% jump in computers and electronics, supported by strong AI and data-center demand. The Communication Services, Information Technology, and Consumer Discretionary sectors are currently leading the market.",
          "tags": [
            "Sector Analysis",
            "Artificial Intelligence",
            "Technology"
          ]
        }
      ]
    }
  ]
}