{
  "generatedAt": "2026-03-16T17:06:00Z",
  "generatedBy": "stocks-agent",
  "feedType": "stocks",
  "title": "Daily Market Digest",
  "subtitle": "March 16, 2026",
  "badge": "LIVE",
  "sections": [
    {
      "id": "market-pulse",
      "title": "Market Pulse",
      "cardType": "breaking",
      "layout": "featured",
      "items": [
        {
          "id": "market-summary-1",
          "headline": "U.S. Markets Open Higher Amid Geopolitical Tensions and AI Optimism",
          "summary": "U.S. stock markets are rebounding at the start of the week, with major indices opening in positive territory, aiming to snap a three-week losing streak for the S&P 500. Despite the positive open, overall market sentiment remains mixed, influenced by ongoing geopolitical conflicts in the Middle East and persistently high crude oil prices. Investors are also closely watching the Federal Reserve's upcoming interest rate decision this week and fresh economic data. Optimism around artificial intelligence (AI) innovation continues to drive gains in the technology sector.",
          "tags": [
            "Market Sentiment",
            "Geopolitics",
            "AI"
          ]
        }
      ]
    },
    {
      "id": "major-indices",
      "title": "Major Indices",
      "cardType": "stat",
      "layout": "grid",
      "items": [
        {
          "id": "stat-sp500",
          "statLabel": "S&P 500",
          "statValue": "6,674.37",
          "statContext": "Up 0.64% (42.2 points) at open."
        },
        {
          "id": "stat-nasdaq",
          "statLabel": "NASDAQ Composite",
          "statValue": "22,340.388",
          "statContext": "Climbed 1.06% (235 points) at open."
        },
        {
          "id": "stat-dow",
          "statLabel": "Dow Jones Industrial Average",
          "statValue": "46,707.4",
          "statContext": "Rose 0.32% (148.9 points) at open."
        }
      ]
    },
    {
      "id": "top-movers",
      "title": "Top Movers",
      "cardType": "stock",
      "layout": "grid",
      "items": [
        {
          "id": "mover-meta",
          "headline": "Meta Platforms",
          "summary": "Shares are up around 2.6%-3% (pre-market +2.98%) following reports of planned major AI-related job cuts to manage costs and a significant $27 billion deal with Dutch cloud provider Nebius for AI capacity.",
          "ticker": "$META",
          "price": "N/A",
          "change": "N/A",
          "changePercent": "+2.6-3%",
          "direction": "up"
        },
        {
          "id": "mover-micron",
          "headline": "Micron Technology",
          "summary": "The stock surged about 4.4% (pre-market +5.46%) after a brokerage firm raised its price target and the company announced plans to build a second manufacturing site in Taiwan to boost advanced DRAM products supply.",
          "ticker": "$MU",
          "price": "N/A",
          "change": "N/A",
          "changePercent": "+4.4%",
          "direction": "up"
        },
        {
          "id": "mover-nvidia",
          "headline": "Nvidia",
          "summary": "Gained approximately 1% (pre-market +2.11%) as investors anticipate major announcements from its annual GTC conference today, focusing on new AI chips and platforms like the 'Vera Rubin' AI architecture.",
          "ticker": "$NVDA",
          "price": "N/A",
          "change": "N/A",
          "changePercent": "+1%",
          "direction": "up"
        },
        {
          "id": "mover-nebius",
          "headline": "Nebius Group",
          "summary": "Experience a significant jump of +13.06% (pre-market +14.27%) due to its substantial $27 billion deal to supply Meta Platforms with dedicated AI capacity.",
          "ticker": "$NBIS",
          "price": "N/A",
          "change": "+$14.75",
          "changePercent": "+13.06%",
          "direction": "up"
        },
        {
          "id": "mover-ulta",
          "headline": "Ulta Beauty Inc.",
          "summary": "Was a major loser on Friday, plummeting 14.2%.",
          "ticker": "$ULTA",
          "price": "N/A",
          "change": "N/A",
          "changePercent": "-14.2%",
          "direction": "down"
        },
        {
          "id": "mover-dollartree",
          "headline": "Dollar Tree",
          "summary": "Fell 6% after reporting mixed fourth-quarter results, with earnings beating expectations but revenue slightly missing forecasts.",
          "ticker": "$DLTR",
          "price": "N/A",
          "change": "N/A",
          "changePercent": "-6%",
          "direction": "down"
        }
      ]
    },
    {
      "id": "market-news",
      "title": "Market News",
      "cardType": "article",
      "layout": "list",
      "items": [
        {
          "id": "news-sector-analysis",
          "headline": "Sector Performance: Tech and Energy Lead, Consumer Discretionary Lags",
          "summary": "Technology and AI-related companies are currently leading the market. The energy sector has also been a top performer year-to-date due to high oil prices, with a noticeable rotation towards defensive areas like consumer staples and utilities. Conversely, consumer discretionary was the only sector experiencing an earnings decline in Q4, and it, along with Industrials and Information Technology, tumbled on Friday.",
          "tags": [
            "Sector Analysis",
            "Technology",
            "Energy",
            "Consumer Discretionary"
          ]
        },
        {
          "id": "news-fed-economic",
          "headline": "Fed Meeting and Key Economic Data Ahead This Week",
          "summary": "The Federal Reserve's interest rate decision is a central focus for markets this week, with expectations for the Fed to hold rates steady at 3.50%-3.75%. Today, the U.S. is releasing industrial production data for February, anticipated to show a 0.2% increase. February's Producer Price Index (PPI) is also expected later in the week. Recent data indicated steady but sticky inflation pressures in February and January, while Q4 2025 U.S. GDP growth was revised down to 0.7%. A U.S. district judge recently blocked the Justice Department's subpoenas against the Federal Reserve and Chair Jerome Powell.",
          "tags": [
            "Federal Reserve",
            "Economic Data",
            "Inflation",
            "GDP"
          ]
        },
        {
          "id": "news-earnings",
          "headline": "Q4 Earnings Season Nearing End with Strong Results; Key Reports Today",
          "summary": "The S&P 500's Q4 earnings season is concluding with robust results, achieving 13.6% earnings growth and 9.2% revenue gains, with ten out of eleven sectors reporting growth. Today, companies such as Agenus ($AGEN), Assertio Therapeutics ($ASRT), Dollar Tree ($DLTR), Ocean Power Technologies ($OPTT), and IHS Holding Limited ($IHS) are expected to report earnings. Last week, Oracle's strong earnings fueled AI investment optimism, while Adobe saw shares drop despite beating forecasts due to a CEO departure.",
          "tags": [
            "Earnings",
            "Corporate Reports"
          ]
        },
        {
          "id": "news-macro-trends",
          "headline": "Geopolitical Tensions, Oil Prices, and AI Continue to Shape Market Landscape",
          "summary": "The ongoing Middle East conflict remains a significant macroeconomic factor, contributing to market uncertainty and elevated crude oil prices near $100 per barrel. Disruptions in the Strait of Hormuz are a key concern for energy supply. Artificial intelligence development continues to be a primary driver for equity markets and corporate earnings. U.S.-China trade negotiations are ongoing in Paris, potentially impacting global supply chains. The credit market is showing signs of stress with downgrades outnumbering upgrades for the fifth consecutive week and rising delinquency rates.",
          "tags": [
            "Geopolitics",
            "Oil Prices",
            "AI",
            "Trade",
            "Credit Market"
          ]
        }
      ]
    }
  ]
}