{
  "generatedAt": "2026-04-25T08:04:00Z",
  "generatedBy": "stocks-agent",
  "feedType": "stocks",
  "title": "Daily Market Digest",
  "subtitle": "April 25, 2026 - Tech-Led Rally Continues Amid Geopolitical Optimism",
  "badge": "LIVE",
  "sections": [
    {
      "id": "market-pulse",
      "title": "Market Pulse",
      "cardType": "breaking",
      "layout": "featured",
      "items": [
        {
          "id": "market-summary-apr25",
          "headline": "U.S. Equities Rally on Tech Strength and Hopes for Mideast De-escalation",
          "summary": "U.S. stock markets closed Friday on a high note, extending a 'risk-on' posture seen throughout April. The Nasdaq Composite and S&P 500 both reached new all-time highs, driven largely by robust performance in the technology and semiconductor sectors. Investor sentiment was further boosted by optimism surrounding potential US-Iran peace talks and clarity on Federal Reserve leadership. The Dow Jones Industrial Average, however, lagged, showing a bifurcation in market performance. Global tensions, particularly in the Middle East, continue to influence commodity markets, though investors appear to be focusing on long-term economic fundamentals. Not financial advice.",
          "tags": [
            "Market Summary",
            "Tech Rally",
            "Geopolitics",
            "Fed"
          ]
        }
      ]
    },
    {
      "id": "major-indices",
      "title": "Major Indices",
      "cardType": "stat",
      "layout": "grid",
      "items": [
        {
          "id": "sp500-performance",
          "statLabel": "S&P 500",
          "statValue": "7,165.08",
          "statContext": "+0.80% Today, New All-Time High."
        },
        {
          "id": "nasdaq-performance",
          "statLabel": "NASDAQ Composite",
          "statValue": "24,836.60",
          "statContext": "+1.63% Today, New All-Time High."
        },
        {
          "id": "dow-performance",
          "statLabel": "Dow Jones Industrial Average",
          "statValue": "49,230.71",
          "statContext": "-0.16% Today."
        }
      ]
    },
    {
      "id": "top-movers",
      "title": "Top Movers",
      "cardType": "stock",
      "layout": "grid",
      "items": [
        {
          "id": "intel-gainer",
          "headline": "Intel Surges on Strong Earnings",
          "summary": "Intel ($INTC) shares surged approximately 23% to an all-time high after reporting a stunning first-quarter earnings beat and providing a positive forecast. Foundry revenue climbed 16% year-over-year, and data center and AI revenue rose 22% amid increasing demand for its CPUs.",
          "ticker": "$INTC",
          "price": "N/A",
          "change": "N/A",
          "changePercent": "+23%",
          "direction": "up"
        },
        {
          "id": "amd-gainer",
          "headline": "AMD Continues Upward Trend",
          "summary": "Advanced Micro Devices ($AMD) saw its stock price soar 14% today, benefiting from the broader semiconductor rally and strong demand in the tech sector.",
          "ticker": "$AMD",
          "price": "N/A",
          "change": "N/A",
          "changePercent": "+14%",
          "direction": "up"
        },
        {
          "id": "infosys-loser",
          "headline": "Infosys Plunges on Muted Outlook",
          "summary": "Infosys ($INFY) shares plunged seven percent on Friday, closing at Rs 1,154.80. The decline was triggered by disappointing earnings and a cautious muted revenue outlook, which impacted the entire IT sector.",
          "ticker": "$INFY",
          "price": "Rs 1,154.80",
          "change": "N/A",
          "changePercent": "-7.00%",
          "direction": "down"
        },
        {
          "id": "hca-loser",
          "headline": "HCA Healthcare Falls Short on Earnings",
          "summary": "HCA Healthcare ($HCA) experienced an 8.76% decline in its stock price after its latest earnings report fell short of analyst expectations, leading the healthcare sector lower.",
          "ticker": "$HCA",
          "price": "N/A",
          "change": "N/A",
          "changePercent": "-8.76%",
          "direction": "down"
        }
      ]
    },
    {
      "id": "market-news",
      "title": "Market News",
      "cardType": "article",
      "layout": "list",
      "items": [
        {
          "id": "sector-tech-semiconductor-rally",
          "headline": "Technology and Semiconductor Sectors Lead Market Gains",
          "summary": "Information Technology was the top-performing sector, gaining 2.46% on Friday, with the semiconductor sector extending its record-breaking streak to 18 consecutive days of gains. Companies like Intel and AMD led the charge, reflecting continued strong demand and investor confidence in tech and AI-related growth.",
          "tags": [
            "Sector Analysis",
            "Technology",
            "Semiconductors",
            "AI"
          ]
        },
        {
          "id": "sector-healthcare-lagging",
          "headline": "Healthcare Sector Lags Amid Earnings Misses",
          "summary": "The healthcare sector was the worst-performing on Friday, down 1.37%. This was largely due to several large-cap names, including HCA Healthcare, posting disappointing earnings reports that fell short of expectations.",
          "tags": [
            "Sector Analysis",
            "Healthcare",
            "Earnings"
          ]
        },
        {
          "id": "economic-fed-leadership",
          "headline": "New Fed Chair Appointment Boosts Market Confidence",
          "summary": "Optimism surrounding the future of monetary policy increased as Kevin Warsh was cleared to take the helm of the U.S. central bank as the new Federal Reserve Chair. This development, along with the Trump administration's decision to suspend legal investigations, has bolstered expectations for a more accommodative policy outlook.",
          "tags": [
            "Economic News",
            "Federal Reserve",
            "Monetary Policy"
          ]
        },
        {
          "id": "economic-earnings-united-bankshares",
          "headline": "United Bankshares Reports Strong Q1 Earnings",
          "summary": "United Bankshares Inc. ($UBSI) announced first-quarter 2026 earnings of $124.2 million, or $0.89 per diluted share. The company highlighted strong earnings, sound asset quality, and efficient capital allocation despite geopolitical and macroeconomic uncertainties.",
          "tags": [
            "Earnings Report",
            "Financials"
          ]
        },
        {
          "id": "economic-earnings-dow-inc",
          "headline": "Dow Inc. Reports Q1 Net Loss, Cites Middle East Conflict Impact",
          "summary": "Dow Inc. ($DOW) reported a GAAP net loss of $445 million for the first quarter of 2026, with net sales down 6% year-over-year. The company noted that its Industrial Intermediates & Infrastructure segment was particularly impacted by the ongoing Middle East conflict.",
          "tags": [
            "Earnings Report",
            "Materials",
            "Geopolitics"
          ]
        },
        {
          "id": "macro-middle-east-tensions",
          "headline": "Middle East Tensions Continue to Affect Energy Markets",
          "summary": "The global natural gas market is expected to remain tight through 2027 due to ongoing Mideast conflict disrupting shipping and delaying LNG supply. Oil prices also climbed on Friday, driven by fears of prolonged supply disruptions through the Strait of Hormuz.",
          "tags": [
            "Macro Trends",
            "Energy Markets",
            "Geopolitics"
          ]
        },
        {
          "id": "macro-q1-earnings-magnificent7",
          "headline": "Magnificent 7 Earnings Focus Shifts to AI Return on Investment",
          "summary": "As the remaining 'Magnificent 7' companies (Nvidia, Apple, Microsoft, Amazon, Alphabet, Meta) prepare to report earnings, investors are shifting their focus from pure AI and datacenter capital expenditures to the return on investment (ROI) from these significant investments.",
          "tags": [
            "Macro Trends",
            "Earnings Season",
            "AI"
          ]
        }
      ]
    }
  ]
}